[
    {
        "id": 1,
        "first_name": "Михаил",
        "last_name": "Дамакальщиков",
        "age": 19,
        "money": 0,
        "phone_number": "89000000000",
        "place_of_residence": {
            "id": 1,
            "name": "Квартира в ЖК 'VIP-супер-крутость'",
            "address": "г. Москва, ул. Лубянка, д. 1",
            "price_per_night": 5000,
            "capacity": 4,
            "available_capacity": 2
        }
    },
    {
        "id": 2,
        "first_name": "Игорь",
        "last_name": "Петров",
        "age": 45,
        "money": 15000,
        "phone_number": "89005553535",
        "place_of_residence": {
            "id": 1,
            "name": "Квартира в ЖК 'VIP-супер-крутость'",
            "address": "г. Москва, ул. Лубянка, д. 1",
            "price_per_night": 5000,
            "capacity": 4,
            "available_capacity": 2
        }
    },
    {
        "id": 3,
        "first_name": "Вася",
        "last_name": "Пупкик",
        "age": 20,
        "money": 3000,
        "phone_number": "+79005002010",
        "place_of_residence": null
    }
]